skytapsdk/__init__.py
skytapsdk/course_manager.py
skytapsdk/helpers.py
skytapsdk/skytap.py
skytapsdk/course_manager_endpoints/__init__.py
skytapsdk/course_manager_endpoints/events.py
skytapsdk/course_manager_endpoints/self_learners.py
skytapsdk/skytap_endpoints/__init__.py
skytapsdk/skytap_endpoints/assets.py
skytapsdk/skytap_endpoints/environments.py
skytapsdk/skytap_endpoints/projects.py
skytapsdk/skytap_endpoints/reports.py
skytapsdk/skytap_endpoints/templates.py
skytapsdk/skytap_endpoints/users.py
skytapsdk-20230414.1.dist-info/LICENSE.md
skytapsdk-20230414.1.dist-info/METADATA
skytapsdk-20230414.1.dist-info/WHEEL
skytapsdk-20230414.1.dist-info/top_level.txt
skytapsdk-20230414.1.dist-info/RECORD
